multisafepay/__init__.py
multisafepay/status.py
multisafepay/test_msp.py
multisafepay/testhttpserver.py
multisafepay/transaction.py
mini_multisafepay-1.0.1.dist-info/METADATA
mini_multisafepay-1.0.1.dist-info/WHEEL
mini_multisafepay-1.0.1.dist-info/entry_points.txt
mini_multisafepay-1.0.1.dist-info/top_level.txt
mini_multisafepay-1.0.1.dist-info/RECORD
