Metadata-Version: 2.1
Name: mini-multisafepay
Version: 1.0.1
Summary: Multisafepay integration
Home-page: https://github.com/jjmurre/mini-multisafepay
Author: Jan Murre
Author-email: jan.murre@catalyz.nl
License: Apache
Platform: UNKNOWN
Classifier: Operating System :: OS Independent
Classifier: Programming Language :: Python
Classifier: Topic :: Internet :: WWW/HTTP
Classifier: Topic :: Software Development :: Libraries :: Python Modules
Requires-Dist: requests
Provides-Extra: testing
Requires-Dist: Otto ; extra == 'testing'
Requires-Dist: pytest ; extra == 'testing'
